jailrootdetector/__init__.py
jailrootdetector/detections.py
jailrootdetector/main.py
jailrootdetector-0.1.2.dist-info/entry_points.txt
jailrootdetector-0.1.2.dist-info/WHEEL
jailrootdetector-0.1.2.dist-info/METADATA
jailrootdetector-0.1.2.dist-info/RECORD
