Metadata-Version: 2.1
Name: jailrootdetector
Version: 0.1.2
Summary: Identify root and jailbreak detection in mobile applications
Home-page: https://gitlab.com/JxTx/jailrootdetector
Author: JxTx
Author-email: joethorpe6@protonmail.com
Requires-Python: >=3.7,<4.0
Classifier: Programming Language :: Python :: 3
Classifier: Programming Language :: Python :: 3.7
Classifier: Programming Language :: Python :: 3.8
Classifier: Programming Language :: Python :: 3.9
Requires-Dist: r2pipe (>=1.5.3,<2.0.0)
Requires-Dist: sh (>=1.14.1,<2.0.0)
Project-URL: Repository, https://gitlab.com/JxTx/jailrootdetector
